botbuilder/applicationinsights/__init__.py
botbuilder/applicationinsights/about.py
botbuilder/applicationinsights/application_insights_telemetry_client.py
botbuilder/applicationinsights/bot_telemetry_processor.py
botbuilder/applicationinsights/django/__init__.py
botbuilder/applicationinsights/django/bot_telemetry_middleware.py
botbuilder/applicationinsights/django/common.py
botbuilder/applicationinsights/django/django_telemetry_processor.py
botbuilder/applicationinsights/django/logging.py
botbuilder/applicationinsights/django/middleware.py
botbuilder/applicationinsights/flask/__init__.py
botbuilder/applicationinsights/flask/flask_telemetry_middleware.py
botbuilder/applicationinsights/flask/flask_telemetry_processor.py
botbuilder/applicationinsights/processor/__init__.py
botbuilder/applicationinsights/processor/telemetry_processor.py
botbuilder_applicationinsights-4.17.1.dist-info/METADATA
botbuilder_applicationinsights-4.17.1.dist-info/WHEEL
botbuilder_applicationinsights-4.17.1.dist-info/top_level.txt
botbuilder_applicationinsights-4.17.1.dist-info/RECORD
